tracer_decorator/__init__.py
tracer_decorator/trace.py
tracer_decorator-0.1.1.dist-info/METADATA
tracer_decorator-0.1.1.dist-info/WHEEL
tracer_decorator-0.1.1.dist-info/RECORD
